[{"id":"default-slice","name":"Default slice","docURL":"...","version":"sktwi1xtmkfgx8626","description":"TextBlueBackground","primary":{"title":[{"type":"heading2","text":"grow sexy e-markets","spans":[]}],"subtitle":[{"type":"paragraph","text":"mesh compelling e-commerce","spans":[]}],"description":[{"type":"paragraph","text":"implement innovative metrics","spans":[]}],"highlightedText":[{"type":"paragraph","text":"disintermediate efficient ROI","spans":[]}],"ctaButtonText":[{"type":"paragraph","text":"target revolutionary infomediaries","spans":[]}],"ctaButtonLink":{"link_type":"Web","url":"https://slicemachine.dev"}},"items":[],"slice_type":"text_blue_background"}]